storyready/__init__.py
storyready-0.0.3.dist-info/METADATA
storyready-0.0.3.dist-info/RECORD
storyready-0.0.3.dist-info/WHEEL
storyready-0.0.3.dist-info/top_level.txt
