Metadata-Version: 2.1
Name: storyready
Version: 0.0.3
Summary: A simple set of checks for typical Agile Story Readiness criteria (GWTS, Story Format,...)
Home-page: https://github.com/DNJC/storyready
Author: David Clarke
Author-email: dnjclarke@gmail.com
License: UNKNOWN
Platform: UNKNOWN
